demosdkpypi/__init__.py
demosdkpypi/hello.py
demosdkpypi/version.py
demosdkpypi-1.9.5.dist-info/METADATA
demosdkpypi-1.9.5.dist-info/WHEEL
demosdkpypi-1.9.5.dist-info/top_level.txt
demosdkpypi-1.9.5.dist-info/RECORD
